druiddb/__init__.py
druiddb/__version__.py
druiddb/console.py
druiddb/db.py
druiddb/druid_sqlalchemy.py
druiddb/exceptions.py
druiddb/sqlalchemy.py
druiddb-0.1.12.dist-info/DESCRIPTION.rst
druiddb-0.1.12.dist-info/METADATA
druiddb-0.1.12.dist-info/RECORD
druiddb-0.1.12.dist-info/WHEEL
druiddb-0.1.12.dist-info/entry_points.txt
druiddb-0.1.12.dist-info/metadata.json
druiddb-0.1.12.dist-info/top_level.txt
