Metadata-Version: 2.0
Name: druiddb
Version: 0.1.12
Summary: Python DB-API and SQLAlchemy interface for Druid.
Home-page: https://github.com/betodealmeida/druid-dbapi
Author: Beto Dealmeida
Author-email: beto@dealmeida.net
License: MIT
Platform: UNKNOWN
Classifier: License :: OSI Approved :: MIT License
Classifier: Programming Language :: Python
Classifier: Programming Language :: Python :: 2.6
Classifier: Programming Language :: Python :: 2.7
Classifier: Programming Language :: Python :: 3
Classifier: Programming Language :: Python :: 3.3
Classifier: Programming Language :: Python :: 3.4
Classifier: Programming Language :: Python :: 3.5
Classifier: Programming Language :: Python :: 3.6
Classifier: Programming Language :: Python :: Implementation :: CPython
Classifier: Programming Language :: Python :: Implementation :: PyPy
Requires-Dist: requests
Requires-Dist: six
Requires-Dist: future-fstrings
Provides-Extra: cli
Requires-Dist: pygments; extra == 'cli'
Requires-Dist: prompt-toolkit; extra == 'cli'
Requires-Dist: tabulate; extra == 'cli'
Provides-Extra: dev
Requires-Dist: nose; extra == 'dev'
Requires-Dist: pipreqs; extra == 'dev'
Requires-Dist: twine; extra == 'dev'
Provides-Extra: sqlalchemy
Requires-Dist: sqlalchemy; extra == 'sqlalchemy'
